pyautonifty/__init__.py
pyautonifty/constants.py
pyautonifty/drawing.py
pyautonifty/drawing_methods.py
pyautonifty/font.py
pyautonifty/fractal_constants.py
pyautonifty/fractal_defn.py
pyautonifty/fractal_generator_fns.py
pyautonifty/fractal_helper_fns.py
pyautonifty/fractal_hull_helper_fns.py
pyautonifty/fractal_piece.py
pyautonifty/fractal_plotter.py
pyautonifty/fractal_runner.py
pyautonifty/fractal_system.py
pyautonifty/helper_fns.py
pyautonifty/numpy_helper_fns.py
pyautonifty/pos.py
pyautonifty/renderer.py
pyautonifty-0.0.1.dist-info/METADATA
pyautonifty-0.0.1.dist-info/WHEEL
pyautonifty-0.0.1.dist-info/top_level.txt
pyautonifty-0.0.1.dist-info/RECORD
