Metadata-Version: 2.1
Name: pyautonifty
Version: 0.0.1
Summary: Automatically and programmatically generate drawing instructions for Nifty.Ink
Home-page: https://github.com/Markichu/PythonAutoNifty
Author: Markichu, Davidryan59, EL-S
Author-email: EL.S13337@gmail.com
License: UNKNOWN
Project-URL: Bug Tracker, https://github.com/Markichu/PythonAutoNifty/issues
Keywords: nifty.ink,NFT,drawing
Platform: UNKNOWN
Classifier: Programming Language :: Python :: 3
Classifier: License :: OSI Approved :: MIT License
Classifier: Operating System :: OS Independent
Requires-Python: >=3.6
Requires-Dist: fonttools (==4.28.2)
Requires-Dist: numpy (==1.21.4)
Requires-Dist: pygame (==2.1.0)
Requires-Dist: scipy (==1.7.2)
Requires-Dist: pillow (==8.4.0)
